gid/__init__.py
gid/guid.py
gid-1.0.1.dist-info/LICENSE
gid-1.0.1.dist-info/WHEEL
gid-1.0.1.dist-info/METADATA
gid-1.0.1.dist-info/RECORD
