Metadata-Version: 2.1
Name: gid
Version: 1.0.1
Summary: Gid is a small library for generating short globally unique, sortable uri safe identifiers.
Home-page: https://github.com/kodemore/gid
License: MIT
Keywords: guid,id,short,sortable,uri-safe,urisafe,uri,safe
Author: Dawid Kraczkowski
Author-email: dawid.kraczkowski@gmail.com
Requires-Python: >=3.8,<4.0
Classifier: Development Status :: 5 - Production/Stable
Classifier: Intended Audience :: Developers
Classifier: License :: OSI Approved :: MIT License
Classifier: Natural Language :: English
Classifier: Programming Language :: Python
Classifier: Programming Language :: Python :: 3
Classifier: Programming Language :: Python :: 3.8
Classifier: Programming Language :: Python :: 3.9
Classifier: Topic :: Software Development :: Libraries
Classifier: Topic :: Software Development :: Libraries :: Python Modules
Classifier: Topic :: Utilities
Project-URL: Documentation, https://github.com/kodemore/gid
Project-URL: Repository, https://github.com/kodemore/gid
